{
  "plugins": {
    "blink.cmp": {
      "rev": "a999ddc",
      "src": "https://github.com/saghen/blink.cmp"
    },
    "mason.nvim": {
      "rev": "ad7146a",
      "src": "https://github.com/mason-org/mason.nvim"
    },
    "neo-tree.nvim": {
      "rev": "9130e58",
      "src": "https://github.com/nvim-neo-tree/neo-tree.nvim",
      "version": "3.0.0 - 4.0.0"
    },
    "nui.nvim": {
      "rev": "de74099",
      "src": "https://github.com/MunifTanjim/nui.nvim"
    },
    "nvim-web-devicons": {
      "rev": "b8221e4",
      "src": "https://github.com/nvim-tree/nvim-web-devicons"
    },
    "plenary.nvim": []
  }
}